kognitos/bdk/__version__.py
kognitos/bdk/poetry/__init__.py
kognitos/bdk/poetry/install_local_k8s.py
kognitos/bdk/poetry/plugin.py
kognitos/bdk/poetry/run.py
kognitos/bdk/poetry/update.py
kognitos/bdk/poetry/usage.py
kognitos_bdk_poetry_plugin-1.6.1.dist-info/METADATA
kognitos_bdk_poetry_plugin-1.6.1.dist-info/WHEEL
kognitos_bdk_poetry_plugin-1.6.1.dist-info/entry_points.txt
kognitos_bdk_poetry_plugin-1.6.1.dist-info/licenses/LICENSE
kognitos_bdk_poetry_plugin-1.6.1.dist-info/RECORD
