Metadata-Version: 2.4
Name: kognitos-bdk-poetry-plugin
Version: 1.6.1
Summary: Kognitos BDK Poetry Plugin
License: Propietary
License-File: LICENSE
Author: Emiliano Lesende
Author-email: emiliano@kognitos.com
Requires-Python: >=3.11,<4.0
Classifier: License :: Other/Proprietary License
Classifier: Programming Language :: Python :: 3
Classifier: Programming Language :: Python :: 3.11
Classifier: Programming Language :: Python :: 3.12
Classifier: Programming Language :: Python :: 3.13
Classifier: Programming Language :: Python :: 3.14
Requires-Dist: dill (>=0.3.8,<0.4.0)
Requires-Dist: docker (>=7.1.0,<8.0.0)
Requires-Dist: poetry (>=2.0,<3.0)
Requires-Dist: pyyaml (>=6.0,<7.0)
Requires-Dist: rich (>=13.7.1,<14.0.0)
Requires-Dist: semver (>=3.0.2,<4.0.0)
Requires-Dist: snakemd (>=2.2.0,<3.0.0)
